tedi/__init__.py
tedi/evidence.py
tedi/gaussian_process.py
tedi/kernels.py
tedi/means.py
tedi/student_process.py
tedi/utils/__init__.py
tedi/utils/evidence.py
tedi/utils/function.py
tedi/utils/kernels.py
tedi/utils/means.py
tedi/utils/time.py
tedi-3.0.1.dist-info/LICENSE
tedi-3.0.1.dist-info/METADATA
tedi-3.0.1.dist-info/WHEEL
tedi-3.0.1.dist-info/RECORD
